vidtoolz_beats/__init__.py
vidtoolz_beats-0.0.1.dist-info/LICENSE
vidtoolz_beats-0.0.1.dist-info/METADATA
vidtoolz_beats-0.0.1.dist-info/WHEEL
vidtoolz_beats-0.0.1.dist-info/entry_points.txt
vidtoolz_beats-0.0.1.dist-info/top_level.txt
vidtoolz_beats-0.0.1.dist-info/RECORD
