Metadata-Version: 2.1
Name: vidtoolz-beats
Version: 0.0.1
Summary: Get beats from a mp3 song
Author: Sukhbinder Singh
License: Apache-2.0
Project-URL: Homepage, https://github.com/sukhbinder/vidtoolz-beats
Project-URL: Changelog, https://github.com/sukhbinder/vidtoolz-beats/releases
Project-URL: Issues, https://github.com/sukhbinder/vidtoolz-beats/issues
Project-URL: CI, https://github.com/sukhbinder/vidtoolz-beats/actions
Classifier: License :: OSI Approved :: Apache Software License
License-File: LICENSE
Requires-Dist: vidtoolz
Requires-Dist: librosa
Provides-Extra: test
Requires-Dist: pytest; extra == "test"
